{
    "blocks": [
        {
            "name": "アダマンタイト",
            "pattern": [
                [0, 1, 0],
                [1, 0, 0],
                [0, 1, 1]
            ],
            "count": 4,
            "score": 120
        },
        {
            "name": "チタニウム",
            "pattern": [
                [1, 1],
                [1, 0],
                [1, 1]
            ],
            "count": 5,
            "score": 120
        },
        {
            "name": "オリハルコン",
            "pattern": [
                [1, 1, 1]
            ],
            "count": 3,
            "score": 60
        },
        {
            "name": "ひすい",
            "pattern": [
                [0, 1, 1],
                [1, 1, 0],
                [0, 1, 0]
            ],
            "count": 5,
            "score": 110
        },
        {
            "name": "ミスリル",
            "pattern": [
                [1, 1, 0],
                [1, 0, 1]
            ],
            "count": 4,
            "score": 85
        },
        {
            "name": "隕鉄",
            "pattern": [
                [0, 1, 0],
                [1, 1, 1],
                [0, 1, 0]
            ],
            "count": 5,
            "score": 113
        },
        {
            "name": "ヒヒイロカネ",
            "pattern": [
                [0, 1, 0],
                [1, 0, 1],
                [0, 1, 0]
            ],
            "count": 4,
            "score": 85
        },
        {
            "name": "石炭",
            "pattern": [
                [0, 1, 0],
                [0, 1, 1],
                [1, 0, 0]
            ],
            "count": 4,
            "score": 85
        },
        {
            "name": "ダマスカス",
            "pattern": [
                [0, 0, 1],
                [0, 1, 0],
                [1, 0, 0]
            ],
            "count": 3,
            "score": 60
        },
        {
            "name": "かいがら",
            "pattern": [
                [1, 1, 1],
                [1, 1, 1],
                [0, 1, 0]
            ],
            "count": 7,
            "score": 150
        },
        {
            "name": "こくようせき",
            "pattern": [
                [1, 1, 1],
                [0, 0, 1]
            ],
            "count": 4,
            "score": 68
        },
        {
            "name": "ダイヤモンド",
            "pattern": [
                [1, 1, 1],
                [1, 1, 1]
            ],
            "count": 6,
            "score": 100
        },
        {
            "name": "だいりせき",
            "pattern": [
                [1, 0],
                [1, 1],
                [1, 1]
            ],
            "count": 5,
            "score": 83
        },
        {
            "name": "サンストーン",
            "pattern": [
                [0, 1, 0],
                [1, 0, 1]
            ],
            "count": 3,
            "score": 50
        },
        {
            "name": "ターコイズ",
            "pattern": [
                [1, 0, 1],
                [1, 1, 0]
            ],
            "count": 4,
            "score": 60
        },
        {
            "name": "なまり",
            "pattern": [
                [0, 0, 1],
                [0, 0, 1],
                [1, 1, 1]
            ],
            "count": 5,
            "score": 73
        },
        {
            "name": "タイガーアイ",
            "pattern": [
                [1, 0],
                [1, 1]
            ],
            "count": 3,
            "score": 40
        },
        {
            "name": "コバルト",
            "pattern": [
                [1, 0, 1],
                [1, 1, 1]
            ],
            "count": 5,
            "score": 68
        },
        {
            "name": "ムーンストーン",
            "pattern": [
                [0, 1],
                [1, 0],
                [0, 1]
            ],
            "count": 3,
            "score": 35
        },
        {
            "name": "アルミニウム",
            "pattern": [
                [1, 0],
                [1, 1],
                [0, 1]
            ],
            "count": 4,
            "score": 50
        },
        {
            "name": "プラチナ",
            "pattern": [
                [0, 1, 1],
                [1, 1, 1]
            ],
            "count": 5,
            "score": 58
        },
        {
            "name": "しんじゅ",
            "pattern": [
                [1, 1],
                [1, 1]
            ],
            "count": 4,
            "score": 40
        },
        {
            "name": "さんご",
            "pattern": [
                [0, 1],
                [1, 1],
                [0, 1]
            ],
            "count": 4,
            "score": 40
        },
        {
            "name": "こはく",
            "pattern": [
                [1],
                [1],
                [1]
            ],
            "count": 3,
            "score": 25
        },
        {
            "name": "化石",
            "pattern": [
                [0, 0, 0, 1],
                [1, 1, 1, 1],
                [1, 0, 0, 0]
            ],
            "count": 6,
            "score": 53
        },
        {
            "name": "きん",
            "pattern": [
                [1, 0, 0],
                [1, 1, 1]
            ],
            "count": 4,
            "score": 38
        },
        {
            "name": "ペリドット",
            "pattern": [
                [1, 1],
                [0, 1]
            ],
            "count": 3,
            "score": 20
        },
        {
            "name": "ぎん",
            "pattern": [
                [1, 1],
                [0, 1],
                [0, 1]
            ],
            "count": 4,
            "score": 28
        },
        {
            "name": "アクアマリン",
            "pattern": [
                [1, 0],
                [1, 0],
                [0, 1]
            ],
            "count": 3,
            "score": 25
        },
        {
            "name": "すず",
            "pattern": [
                [0, 1, 0],
                [1, 1, 1]
            ],
            "count": 4,
            "score": 25
        },
        {
            "name": "銅",
            "pattern": [
                [0, 1, 1],
                [1, 1, 1],
                [0, 1, 0]
            ],
            "count": 6,
            "score": 40
        },
        {
            "name": "ルビー",
            "pattern": [
                [1, 0, 1],
                [0, 1, 0]
            ],
            "count": 4,
            "score": 12
        },
        {
            "name": "鉄",
            "pattern": [
                [1, 1, 0],
                [0, 1, 1]
            ],
            "count": 4,
            "score": 15
        },
        {
            "name": "サファイア",
            "pattern": [
                [1, 0, 0],
                [0, 1, 1]
            ],
            "count": 3,
            "score": 10
        },
        {
            "name": "火打ち石",
            "pattern": [
                [1, 0],
                [1, 0],
                [1, 1]
            ],
            "count": 4,
            "score": 13
        }
        
    ]
}
